kesslergame/__init__.py
kesslergame/_version.py
kesslergame/asteroid.py
kesslergame/bullet.py
kesslergame/collisions.py
kesslergame/controller.py
kesslergame/controller_gamepad.py
kesslergame/kessler_game.py
kesslergame/math_utils.py
kesslergame/mines.py
kesslergame/scenario.py
kesslergame/score.py
kesslergame/settings_dicts.py
kesslergame/ship.py
kesslergame/state_models.py
kesslergame/team.py
kesslergame/graphics/__init__.py
kesslergame/graphics/graphics_base.py
kesslergame/graphics/graphics_handler.py
kesslergame/graphics/graphics_plt.py
kesslergame/graphics/graphics_tk.py
kesslergame/graphics/graphics_ue.py
kesslergame/graphics/images/__init__.py
kesslergame/graphics/images/playerShip1_green.png
kesslergame/graphics/images/playerShip1_orange.png
kesslergame/graphics/images/playerShip2_orange.png
kesslergame/graphics/images/playerShip3_orange.png
kesslergame-2.4.0.dist-info/licenses/LICENSE
kesslergame-2.4.0.dist-info/METADATA
kesslergame-2.4.0.dist-info/WHEEL
kesslergame-2.4.0.dist-info/top_level.txt
kesslergame-2.4.0.dist-info/zip-safe
kesslergame-2.4.0.dist-info/RECORD
