Metadata-Version: 2.4
Name: KesslerGame
Version: 2.4.0
Summary: Asteroids game simulation environment for ML and AI applications
Home-page: https://github.com/ThalesGroup/kessler-game
Author: Zachariah Phillips
Author-email: zach.phillips@defense.us.thalesgroup.com
Maintainer: Timothy Arnett
Maintainer-email: tim.arnett@defense.us.thalesgroup.com
License: Apache 2.0 License
Keywords: artificial intelligence,asteroids,machine learning
Classifier: Programming Language :: Python :: 3
Classifier: Topic :: Scientific/Engineering :: Artificial Intelligence
Classifier: Operating System :: OS Independent
Requires-Python: >=3.10
License-File: LICENSE
Requires-Dist: numpy
Requires-Dist: pillow
Requires-Dist: inputs
Requires-Dist: mypy
Dynamic: license-file
Dynamic: requires-dist
